raincoat/__init__.py
raincoat/config.py
raincoat/helpers.py
raincoat/raincoat.py
raincoat/torrent.py
raincoat_jackett-0.4.dist-info/METADATA
raincoat_jackett-0.4.dist-info/WHEEL
raincoat_jackett-0.4.dist-info/entry_points.txt
raincoat_jackett-0.4.dist-info/top_level.txt
raincoat_jackett-0.4.dist-info/RECORD
