Metadata-Version: 2.1
Name: raincoat-jackett
Version: 0.4
Summary: Raincoat is a tool to search torrents using Jackett and send them to your client.
Home-page: https://github.com/Gabisonfire/raincoat
Author: Gabisonfire
Author-email: gabisonfire@github.com
License: UNKNOWN
Keywords: transmission qbittorrent deluge jackett torrent
Platform: UNKNOWN
Classifier: Programming Language :: Python :: 3 :: Only
Classifier: License :: OSI Approved :: MIT License
Classifier: Operating System :: Unix
Classifier: Topic :: Communications :: File Sharing
Requires-Python: >=3.6
Requires-Dist: requests (==2.18.4)
Requires-Dist: justlog
Requires-Dist: colorama
Requires-Dist: tabulate
Requires-Dist: transmission-clutch
Requires-Dist: deluge-client
Requires-Dist: python-qbittorrent
